matholib/__init__.py
matholib/core.py
matholib/utils.py
matholib-0.1.0.dist-info/licenses/LICENSE
matholib-0.1.0.dist-info/METADATA
matholib-0.1.0.dist-info/WHEEL
matholib-0.1.0.dist-info/top_level.txt
matholib-0.1.0.dist-info/RECORD
