Metadata-Version: 2.4
Name: matholib
Version: 0.1.0
Summary: A simple math library
Author-email: Krishna Tandon <tandonkrishna1208@gmail.com>
Project-URL: Homepage, https://github.com/sleepyowl1208/Matholib
Requires-Python: >=3.7
License-File: LICENSE
Dynamic: license-file
